{"videos":[{"description":"BARULHO NO C\u00c9U DO BRASIL. ESCUTE AGORA MESMO!!!","date":"05\/04\/2020","icon":"youtube","url":"https:\/\/www.youtube.com\/watch?v=S0hVsZhm94Q","source":{"youtube":"https:\/\/www.youtube.com\/embed\/S0hVsZhm94Q"}},{"description":"Barulho no c\u00e9u intriga o mundo","date":"05\/04\/2020","icon":"youtube","url":"https:\/\/www.youtube.com\/watch?v=uanRwBS3VW4","source":{"youtube":"https:\/\/www.youtube.com\/embed\/uanRwBS3VW4"}},{"description":"Vlog 3 Sons estranhos no c\u00e9u do Brasil 2020","date":"05\/04\/2020","icon":"youtube","url":"https:\/\/www.youtube.com\/watch?v=CVt6Rjg8w5g","source":{"youtube":"https:\/\/www.youtube.com\/embed\/CVt6Rjg8w5g"}},{"description":"O come\u00e7o do fim do mundo #barulhonoceu","date":"05\/04\/2020","icon":"youtube","url":"https:\/\/www.youtube.com\/watch?v=QLs3P4MCTHo","source":{"youtube":"https:\/\/www.youtube.com\/embed\/QLs3P4MCTHo"}},{"description":"SONS NO C\u00c9U DO BRASIL\/\/N\u00c3O \u00c9 ATOA QUE VOC\u00ca FOI COLOCADO DE QUARENTENA, ACORDA!","date":"05\/04\/2020","icon":"youtube","url":"https:\/\/www.youtube.com\/watch?v=Tx8p_2j4Dhg","source":{"youtube":"https:\/\/www.youtube.com\/embed\/Tx8p_2j4Dhg"}},{"description":"BARULHO NO C\u00c9U | APOCALIPSE, ALIEN\u00cdGENAS OU GASES?","date":"05\/04\/2020","icon":"youtube","url":"https:\/\/www.youtube.com\/watch?v=W2m94qhN17E","source":{"youtube":"https:\/\/www.youtube.com\/embed\/W2m94qhN17E"}},{"description":"Barulho no C\u00e9u - Movimenta\u00e7\u00e3o Estranha na LUA  - #Ovnis","date":"04\/04\/2020","icon":"youtube","url":"https:\/\/www.youtube.com\/watch?v=A4w7Je81e9Y","source":{"youtube":"https:\/\/www.youtube.com\/embed\/A4w7Je81e9Y"}},{"description":"Barulho no C\u00e9u Abril 2020 (Ou\u00e7a o Som Estranho) + Alien\u00edgena Simbionte Filmado na Praia \u00e9 Real?","date":"04\/04\/2020","icon":"youtube","url":"https:\/\/www.youtube.com\/watch?v=BtQ6x-LTf0w","source":{"youtube":"https:\/\/www.youtube.com\/embed\/BtQ6x-LTf0w"}},{"description":"Tudo sobre #BarulhoNoCeu, plant\u00e3o da internet","date":"04\/04\/2020","icon":"youtube","url":"https:\/\/www.youtube.com\/watch?v=vfLPAnViRfA","source":{"youtube":"https:\/\/www.youtube.com\/embed\/vfLPAnViRfA"}},{"description":"BRASILEIROS EST\u00c3O OUVINDO BARULHO ASSUSTADOR VINDO DO C\u00c9U","date":"04\/04\/2020","icon":"youtube","url":"https:\/\/www.youtube.com\/watch?v=Ud4g6RIKRv0","source":{"youtube":"https:\/\/www.youtube.com\/embed\/Ud4g6RIKRv0"}},{"description":"BARULHO NO CE\u0301U - O QUE E\u0301 O FENO\u0302MENO QUE ESTA\u0301 ASSUSTANDO O MUNDO TODO? | SPACE TODAY TV EP2173","date":"04\/04\/2020","icon":"youtube","url":"https:\/\/www.youtube.com\/watch?v=rNRGPNwN9CY","source":{"youtube":"https:\/\/www.youtube.com\/embed\/rNRGPNwN9CY"}},{"description":"BARULHO NO C\u00c9U! APOCALIPSE? OVNIS?","date":"04\/04\/2020","icon":"youtube","url":"https:\/\/www.youtube.com\/watch?v=l5lnsNU1VtY","source":{"youtube":"https:\/\/www.youtube.com\/embed\/l5lnsNU1VtY"}}],"total":156,"lastUpdated":"04\/06\/2020","cacheControl":"f892b31a6c0d7b4cbae5f681b85bdff0"}