{"videos":[{"country":"1","id":"1261","description":"BARULHOS NO C\u00c9U - SONS ESTRANHOS NO C\u00c9U DO BRASIL!","date":"27\/05\/2020","icon":"youtube","url":"https:\/\/www.youtube.com\/watch?v=X0SBM3qaXqs","source":{"youtube":"https:\/\/www.youtube.com\/embed\/X0SBM3qaXqs"}},{"country":"1","id":"1508","description":"Luzes no c\u00e9u assustam moradores","date":"27\/05\/2020","icon":"youtube","url":"https:\/\/www.youtube.com\/watch?v=VISColLk6nU","source":{"youtube":"https:\/\/www.youtube.com\/embed\/VISColLk6nU"}},{"country":"0","id":"1368","description":"Sounds of the Apocalypse | Trumpet Sounds in the Sky (05.27.2020)","date":"27\/05\/2020","icon":"youtube","url":"https:\/\/www.youtube.com\/watch?v=UvlEPl-yfIM","source":{"youtube":"https:\/\/www.youtube.com\/embed\/UvlEPl-yfIM"}},{"country":"1","id":"1509","description":"Fim dos tempos barulho no c\u00e9u filmado dia 27\/05\/20","date":"27\/05\/2020","icon":"youtube","url":"https:\/\/www.youtube.com\/watch?v=r4g0-ugtHAI","source":{"youtube":"https:\/\/www.youtube.com\/embed\/r4g0-ugtHAI"}},{"country":"1","id":"778","description":"Barulho no c\u00e9u! 27\/05\/2020 Betim (MG) #barulhonoceu","date":"27\/05\/2020","icon":"youtube","url":"https:\/\/www.youtube.com\/watch?v=m2bXmLBXGH8","source":{"youtube":"https:\/\/www.youtube.com\/embed\/m2bXmLBXGH8"}},{"country":"1","id":"873","description":"BARULHOS NO C\u00c9U DE MADRUGADA, OVNIS HOJE, CHINA FICA 10 MINUTOS NO ESCURO, OVNI EM CAMINH\u00c3O","date":"27\/05\/2020","icon":"youtube","url":"https:\/\/www.youtube.com\/watch?v=_GDBKWTPqxE","source":{"youtube":"https:\/\/www.youtube.com\/embed\/_GDBKWTPqxE"}},{"country":"0","id":"1147","description":"Relaxing video. TIME-LAPS sky. Beautiful music. Nature summer sounds.","date":"27\/05\/2020","icon":"youtube","url":"https:\/\/www.youtube.com\/watch?v=TrDhkzBV9D0","source":{"youtube":"https:\/\/www.youtube.com\/embed\/TrDhkzBV9D0"}},{"country":"1","id":"772","description":"BARULHOS NO C\u00c9U 2020 - BARULHO ESTRANHO \u00c9 OUVIDO NO C\u00c9U HOJE #barulhonoceu","date":"27\/05\/2020","icon":"youtube","url":"https:\/\/www.youtube.com\/watch?v=_aNzE_-tGjk","source":{"youtube":"https:\/\/www.youtube.com\/embed\/_aNzE_-tGjk"}},{"country":"0","id":"1071","description":"MISTERIOS 2020 (LOS RUIDOS DEL CIELO)ANDRESPONCE","date":"26\/05\/2020","icon":"youtube","url":"https:\/\/www.youtube.com\/watch?v=l1C2hH688zE","source":{"youtube":"https:\/\/www.youtube.com\/embed\/l1C2hH688zE"}},{"country":"1","id":"876","description":"luzes se movem no c\u00e9u 20\/05 - UFOS\/OVNIS","date":"26\/05\/2020","icon":"youtube","url":"https:\/\/www.youtube.com\/watch?v=hM_UaKoBzfM","source":{"youtube":"https:\/\/www.youtube.com\/embed\/hM_UaKoBzfM"}},{"country":"1","id":"768","description":"Gravei este v\u00eddeo em abril de 2020 #ovni #ufo #barulhonoceu","date":"26\/05\/2020","icon":"youtube","url":"https:\/\/www.youtube.com\/watch?v=AE3MOS86xQQ","source":{"youtube":"https:\/\/www.youtube.com\/embed\/AE3MOS86xQQ"}},{"country":"0","id":"1426","description":"26.05.2020 strange noise in the sky warning explicit language","date":"26\/05\/2020","icon":"youtube","url":"https:\/\/www.youtube.com\/watch?v=y2lCIJPMZPI","source":{"youtube":"https:\/\/www.youtube.com\/embed\/y2lCIJPMZPI"}}],"total":"837","lastUpdated":"04\/06\/2020","cacheControl":"db8c2c981dc67cea2d141264a76a7fc0"}