{"videos":[{"country":"0","id":"1145","description":"Strange Sounds from the Sky \/ Vienna Austria","date":"02\/04\/2020","icon":"youtube","url":"https:\/\/www.youtube.com\/watch?v=zARTDkjHDM8","source":{"youtube":"https:\/\/www.youtube.com\/embed\/zARTDkjHDM8"}},{"country":"0","id":"1416","description":"Strange noise in the sky in South Philadelphia","date":"02\/04\/2020","icon":"youtube","url":"https:\/\/www.youtube.com\/watch?v=yd0r7zWb-S8","source":{"youtube":"https:\/\/www.youtube.com\/embed\/yd0r7zWb-S8"}},{"country":"0","id":"1360","description":"Strange Sounds in the Sky April 2020","date":"02\/04\/2020","icon":"youtube","url":"https:\/\/www.youtube.com\/watch?v=J6U2_5qMsL4","source":{"youtube":"https:\/\/www.youtube.com\/embed\/J6U2_5qMsL4"}},{"country":"1","id":"939","description":"NUVEM DE GAFANHOTOS DESTRUINDO PLANTA\u00c7\u00d5ES, FIM DOS TEMPOS, JESUS EST\u00c1 VOLTANDO","date":"02\/04\/2020","icon":"youtube","url":"https:\/\/www.youtube.com\/watch?v=KpC4YefbeMU","source":{"youtube":"https:\/\/www.youtube.com\/embed\/KpC4YefbeMU"}},{"country":"0","id":"1110","description":"Ruidos de trompetas\ud83c\udfbaen el cielo\ud83d\ude31\u00a1\u00a1incre\u00edble!! En Argentina \ud83c\udde6\ud83c\uddf7 &quot;El Bols\u00f3n&quot;","date":"01\/04\/2020","icon":"youtube","url":"https:\/\/www.youtube.com\/watch?v=VQcRZqVi3Zg","source":{"youtube":"https:\/\/www.youtube.com\/embed\/VQcRZqVi3Zg"}},{"country":"0","id":"1068","description":"Sonidos fuertes en el cielo y avistamientos de objetos extra\u00f1os , alguien sabe que es ? Ser\u00e1 el fin","date":"31\/03\/2020","icon":"youtube","url":"https:\/\/www.youtube.com\/watch?v=bK8TrJLUXbs","source":{"youtube":"https:\/\/www.youtube.com\/embed\/bK8TrJLUXbs"}},{"country":"0","id":"1282","description":"Extra\u00f1o ruido \u201cdel cielo\u201d en Envigado Antioquia Colombia 29 Marzo 2020","date":"30\/03\/2020","icon":"youtube","url":"https:\/\/www.youtube.com\/watch?v=f3Zq7D5Wr9Q","source":{"youtube":"https:\/\/www.youtube.com\/embed\/f3Zq7D5Wr9Q"}},{"country":"1","id":"859","description":"DiAS DE QUARENTENA E O C\u00c9U ESTA ESTRANHO.","date":"28\/03\/2020","icon":"youtube","url":"https:\/\/www.youtube.com\/watch?v=YoKOfhoOGu8","source":{"youtube":"https:\/\/www.youtube.com\/embed\/YoKOfhoOGu8"}},{"country":"0","id":"1100","description":"Extra\u00f1o ruido aparece en el cielo Uruguay","date":"28\/03\/2020","icon":"youtube","url":"https:\/\/www.youtube.com\/watch?v=Lw0-Vc3GiVA","source":{"youtube":"https:\/\/www.youtube.com\/embed\/Lw0-Vc3GiVA"}},{"country":"0","id":"1099","description":"Extra\u00f1os ruidos en el cielo de Monter\u00eda C\u00f3rdoba..","date":"27\/03\/2020","icon":"youtube","url":"https:\/\/www.youtube.com\/watch?v=fGQdYqJW2i0","source":{"youtube":"https:\/\/www.youtube.com\/embed\/fGQdYqJW2i0"}},{"country":"0","id":"1237","description":"In the Last Days! Trumpet sound in China","date":"27\/03\/2020","icon":"youtube","url":"https:\/\/www.youtube.com\/watch?v=mSO82nfeVBY","source":{"youtube":"https:\/\/www.youtube.com\/embed\/mSO82nfeVBY"}},{"country":"0","id":"1075","description":"SONIDOS EXTRA\u00d1OS EN EL CIELO DE URUGUAY","date":"27\/03\/2020","icon":"youtube","url":"https:\/\/www.youtube.com\/watch?v=SYEhoNpeVyo","source":{"youtube":"https:\/\/www.youtube.com\/embed\/SYEhoNpeVyo"}}],"cacheControl":"d068d63f1e4122795a3b9bea60ac5889","page":23}