{"videos":[{"country":"0","id":"2624","description":"ALIENS?? STRANGE NOISES IN SKY!!!","date":"09\/05\/2013","icon":"youtube","url":"https:\/\/www.youtube.com\/watch?v=7Q9KMwyC9uM","source":{"youtube":"https:\/\/www.youtube.com\/embed\/7Q9KMwyC9uM"}},{"country":"0","id":"2130","description":"Ruidos extra\u00f1os en el cielo","date":"11\/04\/2013","icon":"youtube","url":"https:\/\/www.youtube.com\/watch?v=Wb5O7v5sHzU","source":{"youtube":"https:\/\/www.youtube.com\/embed\/Wb5O7v5sHzU"}},{"country":"0","id":"2793","description":"The trumpet sounds of Austral penguins","date":"07\/03\/2013","icon":"youtube","url":"https:\/\/www.youtube.com\/watch?v=G5Rzkg3SrbM","source":{"youtube":"https:\/\/www.youtube.com\/embed\/G5Rzkg3SrbM"}},{"country":"0","id":"2559","description":"ruidos del cielo","date":"25\/02\/2013","icon":"youtube","url":"https:\/\/www.youtube.com\/watch?v=ktXYzIn83UI","source":{"youtube":"https:\/\/www.youtube.com\/embed\/ktXYzIn83UI"}},{"country":"0","id":"2076","description":"Mouth Trumpet - Tutorial","date":"02\/01\/2013","icon":"youtube","url":"https:\/\/www.youtube.com\/watch?v=5R2MEnm_EXY","source":{"youtube":"https:\/\/www.youtube.com\/embed\/5R2MEnm_EXY"}},{"country":"0","id":"2811","description":"RUIDOS EN EL CIELO DE IZTAPALAPA","date":"14\/11\/2012","icon":"youtube","url":"https:\/\/www.youtube.com\/watch?v=DeLsN3ry0E8","source":{"youtube":"https:\/\/www.youtube.com\/embed\/DeLsN3ry0E8"}},{"country":"0","id":"2488","description":"WEIRD SKY NOISE ATMOSPHERIC,  SE LONDON UK  8\/11\/12","date":"08\/11\/2012","icon":"youtube","url":"https:\/\/www.youtube.com\/watch?v=p0LX95UR7ps","source":{"youtube":"https:\/\/www.youtube.com\/embed\/p0LX95UR7ps"}},{"country":"0","id":"2715","description":"CAPITULO 19 LA LUNA COMO DE SANGRE Y RUIDOS EN EL CIELO","date":"27\/10\/2012","icon":"youtube","url":"https:\/\/www.youtube.com\/watch?v=YELVVD2WEIk","source":{"youtube":"https:\/\/www.youtube.com\/embed\/YELVVD2WEIk"}},{"country":"0","id":"2346","description":"strange noise in sky over Pyrenees fr. 18.10.12","date":"18\/10\/2012","icon":"youtube","url":"https:\/\/www.youtube.com\/watch?v=YfpO5XYaVeg","source":{"youtube":"https:\/\/www.youtube.com\/embed\/YfpO5XYaVeg"}},{"country":"0","id":"1611","description":"12\/10\/2012 Ruidos en el cielo Xalapa, Ver. pt.1","date":"13\/10\/2012","icon":"youtube","url":"https:\/\/www.youtube.com\/watch?v=kwEg2MGF520","source":{"youtube":"https:\/\/www.youtube.com\/embed\/kwEg2MGF520"}},{"country":"1","id":"2269","description":"Anjos de Deus!!! - Pe. Marcelo Rossi","date":"12\/10\/2012","icon":"youtube","url":"https:\/\/www.youtube.com\/watch?v=H5_SaazkWsw","source":{"youtube":"https:\/\/www.youtube.com\/embed\/H5_SaazkWsw"}},{"country":"0","id":"2483","description":"Wierd, strange Sky Noise, Beaverlodge,Alberta,Canada Oct 12 2011 pt 1","date":"28\/09\/2012","icon":"youtube","url":"https:\/\/www.youtube.com\/watch?v=nzp6jAwKIeo","source":{"youtube":"https:\/\/www.youtube.com\/embed\/nzp6jAwKIeo"}}],"cacheControl":"559e6d6c7e96fc21704c7a0221d9af8d","page":76}