{"videos":[{"country":"0","id":"2026","description":"PUDE GRABAR EL SONIDO QUE SE ESCUCHA DE NOCHE \ud83d\ude31\ud83d\ude31\ud83d\ude31\ud83d\ude31 CIELOMOTO O THE HUM o COMO SE LLAME !!!","date":"08\/04\/2020","icon":"youtube","url":"https:\/\/www.youtube.com\/watch?v=vtGavyBKbgA","source":{"youtube":"https:\/\/www.youtube.com\/embed\/vtGavyBKbgA"}},{"country":"1","id":"1626","description":"SOM DE TROMBETA NO C\u00c9U 2020\/ BARULHO NO C\u00c9U","date":"08\/04\/2020","icon":"youtube","url":"https:\/\/www.youtube.com\/watch?v=0za-BcWrg5Y","source":{"youtube":"https:\/\/www.youtube.com\/embed\/0za-BcWrg5Y"}},{"country":"0","id":"2055","description":"Ruidos en el cielo de Argentina Abril 8-2020","date":"08\/04\/2020","icon":"youtube","url":"https:\/\/www.youtube.com\/watch?v=eHvigZZz-UI","source":{"youtube":"https:\/\/www.youtube.com\/embed\/eHvigZZz-UI"}},{"country":"0","id":"2073","description":"Ruido en el cielo Chile","date":"08\/04\/2020","icon":"youtube","url":"https:\/\/www.youtube.com\/watch?v=NZFjKzeai4I","source":{"youtube":"https:\/\/www.youtube.com\/embed\/NZFjKzeai4I"}},{"country":"0","id":"2096","description":"Cielomoto barrio20 de junio !!\u00a1\u00a1\u00a1","date":"07\/04\/2020","icon":"youtube","url":"https:\/\/www.youtube.com\/watch?v=Y6c8ki0y0Qc","source":{"youtube":"https:\/\/www.youtube.com\/embed\/Y6c8ki0y0Qc"}},{"country":"1","id":"2004","description":"Fam\u00edlia: caminho para o C\u00e9u | FAZENDO BARULHO [REPRISE]","date":"07\/04\/2020","icon":"youtube","url":"https:\/\/www.youtube.com\/watch?v=UY-eNKeDg1Y","source":{"youtube":"https:\/\/www.youtube.com\/embed\/UY-eNKeDg1Y"}},{"country":"0","id":"2285","description":"Ruidos en el cielo","date":"07\/04\/2020","icon":"youtube","url":"https:\/\/www.youtube.com\/watch?v=3btWWj8POUY","source":{"youtube":"https:\/\/www.youtube.com\/embed\/3btWWj8POUY"}},{"country":"0","id":"2125","description":"Ruidos en el cielo","date":"07\/04\/2020","icon":"youtube","url":"https:\/\/www.youtube.com\/watch?v=JflG67L8U_8","source":{"youtube":"https:\/\/www.youtube.com\/embed\/JflG67L8U_8"}},{"country":"0","id":"2111","description":"Ruidos en el cielo 2020","date":"07\/04\/2020","icon":"youtube","url":"https:\/\/www.youtube.com\/watch?v=l21UrTePQI4","source":{"youtube":"https:\/\/www.youtube.com\/embed\/l21UrTePQI4"}},{"country":"0","id":"2122","description":"Ruidos extra\u00f1os en el cielo de Uruguay. 04\/04\/20","date":"07\/04\/2020","icon":"youtube","url":"https:\/\/www.youtube.com\/watch?v=pgo7TYCTk6o","source":{"youtube":"https:\/\/www.youtube.com\/embed\/pgo7TYCTk6o"}},{"country":"0","id":"2286","description":"Extra\u00f1o ruido en el cielo, M\u00e9xico.","date":"07\/04\/2020","icon":"youtube","url":"https:\/\/www.youtube.com\/watch?v=l8UgvwyPImY","source":{"youtube":"https:\/\/www.youtube.com\/embed\/l8UgvwyPImY"}},{"country":"0","id":"2121","description":"Ruido Extra\u00f1o en el cielo","date":"07\/04\/2020","icon":"youtube","url":"https:\/\/www.youtube.com\/watch?v=9IU5vxb4ZAM","source":{"youtube":"https:\/\/www.youtube.com\/embed\/9IU5vxb4ZAM"}}],"cacheControl":"9191363f6ca891cb06f10757944a72b9","page":81}